pyquafu-0.4.5.dist-info/RECORD
pyquafu-0.4.5.dist-info/WHEEL
pyquafu-0.4.5.dist-info/METADATA
pyquafu-0.4.5.dist-info/licenses/LICENSE
quafu/requirements.txt
quafu/__init__.py
quafu/benchmark/unitary_test.py
quafu/benchmark/__init__.py
quafu/benchmark/deutsch_jozsa.py
quafu/benchmark/variational_n4.py
quafu/benchmark/variational/ladder_circuit.py
quafu/benchmark/variational/brickwall_circuit.py
quafu/transpiler/__init__.py
quafu/transpiler/backends/backend.py
quafu/transpiler/backends/__init__.py
quafu/transpiler/passflow/passflow.py
quafu/transpiler/passflow/__init__.py
quafu/transpiler/graph/couplinggraph.py
quafu/transpiler/graph/similar_substructure.py
quafu/transpiler/graph/__init__.py
quafu/transpiler/graph/graphkernel.py
quafu/transpiler/graph/circuitgraph.py
quafu/transpiler/graph/graphmapping.py
quafu/transpiler/passes/basepass.py
quafu/transpiler/passes/__init__.py
quafu/transpiler/passes/example_pass.py
quafu/transpiler/passes/datadict.py
quafu/transpiler/passes/model.py
quafu/transpiler/passes/mapping/__init__.py
quafu/transpiler/passes/mapping/baselayout.py
quafu/transpiler/passes/synthesis/__init__.py
quafu/transpiler/utils/__init__.py
quafu/transpiler/utils/reverse_circuit.py
quafu/transpiler/results/__init__.py
quafu/transpiler/compiler/compiler_visualization.py
quafu/transpiler/compiler/compiler.py
quafu/transpiler/compiler/__init__.py
quafu/tasks/task_database.py
quafu/tasks/tasks.py
quafu/tasks/__init__.py
quafu/circuits/quantum_register.py
quafu/circuits/__init__.py
quafu/circuits/quantum_circuit.py
quafu/circuits/classical_register.py
quafu/backends/__init__.py
quafu/backends/backends.py
quafu/qfasm/qfasm_lexer.py
quafu/qfasm/qfasm_parser.py
quafu/qfasm/qfasm_utils.py
quafu/qfasm/__init__.py
quafu/qfasm/exceptions.py
quafu/qfasm/qfasm_convertor.py
quafu/qfasm/qelib1.inc
quafu/simulators/qfvm.cpython-313-darwin.so
quafu/simulators/__init__.py
quafu/simulators/default_simulator.py
quafu/simulators/simulator.py
quafu/simulators/torch.py
quafu/algorithms/interface_provider.py
quafu/algorithms/ansatz.py
