Metadata-Version: 2.2
Name: pyquafu
Version: 0.4.5
Summary: Python toolkit for Quafu-Cloud
Author-Email: ssli <ssli@iphy.ac.cn>
License: Apache-2.0
Project-URL: Homepage, https://github.com/ScQ-Cloud/pyquafu
Requires-Python: >=3.8
Requires-Dist: autograd>=1.6.2
Requires-Dist: graphviz>=0.14.2
Requires-Dist: ipython>=8.14.0
Requires-Dist: matplotlib>=3.5.2
Requires-Dist: networkx>=2.6.3
Requires-Dist: numpy<2.0.0,>=1.20.3
Requires-Dist: ply~=3.11
Requires-Dist: pybind11>=2.10.3
Requires-Dist: requests>=2.26.0
Requires-Dist: scipy>=1.8.1
Requires-Dist: sparse>=0.13.0
Provides-Extra: dev
Requires-Dist: pytest; extra == "dev"
Requires-Dist: pre-commit; extra == "dev"
